.gitignore
COPYING.txt
MANIFEST.in
Makefile
README.rst
TODO.org
TODO.org_archive
setup.py
cochlear_nucleus/__init__.py
cochlear_nucleus.egg-info/PKG-INFO
cochlear_nucleus.egg-info/SOURCES.txt
cochlear_nucleus.egg-info/dependency_links.txt
cochlear_nucleus.egg-info/top_level.txt
cochlear_nucleus/brn/__init__.py
cochlear_nucleus/brn/anf.py
cochlear_nucleus/brn/gbc.py
cochlear_nucleus/nrn/RecovExp.mod
cochlear_nucleus/nrn/__init__.py
cochlear_nucleus/nrn/endbulb_weights.csv
cochlear_nucleus/nrn/gbc.py
cochlear_nucleus/nrn/hcno.mod
cochlear_nucleus/nrn/ih.mod
cochlear_nucleus/nrn/ka.mod
cochlear_nucleus/nrn/kht.mod
cochlear_nucleus/nrn/klt.mod
cochlear_nucleus/nrn/na.mod
cochlear_nucleus/nrn/na_rothman93.mod
cochlear_nucleus/nrn/na_spirou2005.mod
cochlear_nucleus/nrn/recov2exp.mod
examples/brian_gbc_anf_demo.py
examples/brian_gbc_simple_demo.py
examples/nrn_gbc_demo.py
examples/nrn_gbc_demo_with_default_weights.py
tests/test_gbc.py