Metadata-Version: 1.1
Name: cochlear-nucleus
Version: 2
Summary: Models of cochlear nucleus neurons
Home-page: https://github.com/mrkrd/cochlear_nucleus
Author: Marek Rudnicki
Author-email: marek.rudnicki@tum.de
License: GPLv3+
Download-URL: https://github.com/mrkrd/cochlear_nucleus/tarball/master
Platform: UNKNOWN
Classifier: Development Status :: 5 - Production/Stable
Classifier: Environment :: Console
Classifier: Intended Audience :: Science/Research
Classifier: License :: OSI Approved :: GNU General Public License v3 or later (GPLv3+)
Classifier: Operating System :: POSIX
Classifier: Operating System :: Microsoft :: Windows
Classifier: Operating System :: MacOS :: MacOS X
Classifier: Programming Language :: Python
Classifier: Programming Language :: Python :: 2.7
